restful_starlette_admin/__init__.py
restful_starlette_admin/admin.py
restful_starlette_admin/file_content.py
restful_starlette_admin/structure.py
restful_starlette_admin-0.0.9.dist-info/LICENSE
restful_starlette_admin-0.0.9.dist-info/METADATA
restful_starlette_admin-0.0.9.dist-info/WHEEL
restful_starlette_admin-0.0.9.dist-info/entry_points.txt
restful_starlette_admin-0.0.9.dist-info/top_level.txt
restful_starlette_admin-0.0.9.dist-info/RECORD
