Metadata-Version: 2.1
Name: restful-starlette-admin
Version: 0.0.9
Summary: Admin CLI for restful-starlette
Author: TianMa Chen
Author-email: 819252022@qq.com
License: BSD-3-Clause
Platform: UNKNOWN
Requires-Python: >=3.7
License-File: LICENSE
Requires-Dist: click (~=8.0.3)
Requires-Dist: restful-starlette (>=0.0.3)
